setup.py
pyad/__init__.py
pyad/adbase.py
pyad/adcomputer.py
pyad/adcontainer.py
pyad/addomain.py
pyad/adgroup.py
pyad/adobject.py
pyad/adquery.py
pyad/adsearch.py
pyad/aduser.py
pyad/pyad.py
pyad/pyadconstants.py
pyad/pyadexceptions.py
pyad/pyadutils.py
pyad.egg-info/PKG-INFO
pyad.egg-info/SOURCES.txt
pyad.egg-info/dependency_links.txt
pyad.egg-info/requires.txt
pyad.egg-info/top_level.txt