Metadata-Version: 1.0
Name: pyad
Version: 0.5.08
Summary: An Object-Oriented Active Directory management framework built on ADSI
Home-page: https://zakird.com/pyad
Author: Zakir Durumeric
Author-email: zakird@gmail.com
License: Apache License, Version 2.0
Download-URL: https://github.com/zakird/pyad/
Keywords: python microsoft windows active directory AD adsi
Platform: UNKNOWN
Classifier: Development Status :: 5 - Production/Stable
Classifier: License :: OSI Approved :: Apache Software License
Classifier: Intended Audience :: System Administrators
Classifier: Natural Language :: English
Classifier: Operating System :: Microsoft :: Windows
Classifier: Topic :: System :: Systems Administration :: Authentication/Directory :: LDAP
